project_scaffolder-0.1.0.dist-info/licenses/LICENSE
scaffold/__init__.py
scaffold/cli.py
scaffold/generator.py
project_scaffolder-0.1.0.dist-info/METADATA
project_scaffolder-0.1.0.dist-info/WHEEL
project_scaffolder-0.1.0.dist-info/entry_points.txt
project_scaffolder-0.1.0.dist-info/top_level.txt
project_scaffolder-0.1.0.dist-info/RECORD
