Metadata-Version: 2.4
Name: project-scaffolder
Version: 0.1.0
Summary: Generate project folders and files from a tree-style text file
Author-email: Dipak Pulami Magar <dpm.it24800@gmail.com>
License: MIT
Keywords: scaffold,project,tree,cli
Requires-Python: >=3.8
License-File: LICENSE
Dynamic: license-file
